{
  "title": "Список допомоги",
  "description": "Ці речі допоможуть дітям у навчанні та розвитку. До придбаних товарів додаються чеки.",
  "expandHint": "Спочатку заплановані матеріали допомоги, завершені окремим фінансуванням до переїзду",
  "statusLabels": {
    "pending": "Очікує",
    "purchased": "Придбано",
    "delivered": "Доставлено"
  },
  "items": [
    {
      "item": "Іграшковий будинок",
      "itemOriginal": "Іграшковий будинок",
      "category": "toys",
      "quantity": 1,
      "unitPrice": { "uah": 1200, "usd": 29 },
      "status": "pending",
      "forChild": "Дівчатка"
    },
    {
      "item": "Лялька",
      "itemOriginal": "Лялька",
      "category": "toys",
      "quantity": 3,
      "unitPrice": { "uah": 450, "usd": 11 },
      "status": "pending",
      "forChild": "Марійка, Софія, Вікторія"
    },
    {
      "item": "Набір книг «Пірати Карибського моря»",
      "itemOriginal": "Набір книг «Пірати Карибського моря»",
      "category": "books",
      "quantity": 1,
      "unitPrice": { "uah": 380, "usd": 9 },
      "status": "pending"
    },
    {
      "item": "Набір книг «Гаррі Поттер»",
      "itemOriginal": "Набір книг «Гаррі Поттер»",
      "category": "books",
      "quantity": 1,
      "unitPrice": { "uah": 1858, "usd": 45 },
      "status": "pending"
    },
    {
      "item": "Дитяча енциклопедія",
      "itemOriginal": "Дитяча енциклопедія",
      "category": "books",
      "quantity": 1,
      "unitPrice": { "uah": 1446, "usd": 35 },
      "status": "pending"
    },
    {
      "item": "Збірка класичних казок",
      "itemOriginal": "Збірка класичних казок",
      "category": "books",
      "quantity": 1,
      "unitPrice": { "uah": 1033, "usd": 25 },
      "status": "pending"
    },
    {
      "item": "Пазли",
      "itemOriginal": "Пазли",
      "category": "toys",
      "quantity": 5,
      "unitPrice": { "uah": 180, "usd": 4 },
      "status": "pending"
    },
    {
      "item": "Електричний розвиваючий конструктор для дітей",
      "itemOriginal": "Електричний розвиваючий конструктор для дітей",
      "category": "educational",
      "quantity": 2,
      "unitPrice": { "uah": 850, "usd": 21 },
      "status": "pending"
    },
    {
      "item": "Книги: серія «Винні», «Повернення Рейчал Прайз»",
      "itemOriginal": "Книги. Серія «Винні», «Повернення Рейчал Прайз»",
      "category": "books",
      "quantity": 1,
      "unitPrice": { "uah": 320, "usd": 8 },
      "status": "pending",
      "forChild": "Катя"
    },
    {
      "item": "Конструктор для Діми",
      "itemOriginal": "Конструктор для Діми",
      "category": "toys",
      "quantity": 2,
      "unitPrice": { "uah": 650, "usd": 16 },
      "status": "pending",
      "forChild": "Діма"
    },
    {
      "item": "Дитячий матрас (1.20×0.60)",
      "itemOriginal": "Дитячий матрас 1.20 / 60",
      "category": "furniture",
      "quantity": 1,
      "unitPrice": { "uah": 2800, "usd": 68 },
      "status": "pending"
    },
    {
      "item": "Залізна шафа",
      "itemOriginal": "Шкаф жилізний",
      "category": "furniture",
      "quantity": 1,
      "unitPrice": { "uah": 4500, "usd": 109 },
      "status": "pending"
    },
    {
      "item": "Набір свіжих фруктів",
      "itemOriginal": "Набір свіжих фруктів",
      "category": "food",
      "quantity": 3,
      "unitPrice": { "uah": 2065, "usd": 50 },
      "status": "pending"
    }
  ],
  "total": {
    "items": 23,
    "totalCost": { "uah": 24982, "usd": 605 }
  },
  "exchangeRateNote": "Курс обміну: 1 USD ≈ 41.3 UAH",
  "note": "Залишок пожертвувань після придбання товарів буде передано безпосередньо готівкою",
  "receipts": {
    "description": "Чеки на покупки (завантажуються після покупки)",
    "images": []
  },
  "itemsV2": [
    {
      "item": "Фрукти",
      "itemOriginal": "Фрукти",
      "category": "food",
      "quantity": 1,
      "unitPrice": { "uah": 4372.10, "usd": 106 },
      "status": "delivered"
    },
    {
      "item": "Їжа",
      "itemOriginal": "Їжа",
      "category": "food",
      "quantity": 1,
      "unitPrice": { "uah": 7745.56, "usd": 188 },
      "status": "delivered"
    },
    {
      "item": "Іграшки",
      "itemOriginal": "Іграшки",
      "category": "toys",
      "quantity": 1,
      "unitPrice": { "uah": 10187.50, "usd": 247 },
      "status": "delivered"
    },
    {
      "item": "Пальне для швидкої допомоги",
      "itemOriginal": "Пальне для швидкої допомоги",
      "category": "transport",
      "quantity": 1,
      "unitPrice": { "uah": 7131.93, "usd": 173 },
      "status": "delivered"
    }
  ],
  "totalV2": {
    "items": 4,
    "totalCost": { "uah": 29437.09, "usd": 713 }
  },
  "receiptsV2": {
    "description": "Чеки на покупки",
    "images": [
      "/images/projects/project-4/details/receipts/img_5529.webp",
      "/images/projects/project-4/details/receipts/img_5530.webp",
      "/images/projects/project-4/details/receipts/img_5531.webp",
      "/images/projects/project-4/details/receipts/img_5532.webp",
      "/images/projects/project-4/details/receipts/img_5533.webp",
      "/images/projects/project-4/details/receipts/sydorenko_fruit.webp"
    ]
  }
}
